youtubesearch/__init__.py
youtubesearch/api_helper.py
youtubesearch/configuration.py
youtubesearch/decorators.py
youtubesearch/youtubesearch_client.py
youtubesearch/controllers/__init__.py
youtubesearch/controllers/base_controller.py
youtubesearch/controllers/simple_list_search_controller.py
youtubesearch/exceptions/__init__.py
youtubesearch/exceptions/api_exception.py
youtubesearch/http/__init__.py
youtubesearch/http/http_call_back.py
youtubesearch/http/http_client.py
youtubesearch/http/http_method_enum.py
youtubesearch/http/http_request.py
youtubesearch/http/http_response.py
youtubesearch/http/requests_client.py
youtubesearch/models/__init__.py
youtubesearch/models/search_enum.py
youtubesearch/utilities/__init__.py
youtubesearch/utilities/file_wrapper.py
Youtube_Video_Search_API-1.0.dist-info/LICENSE
Youtube_Video_Search_API-1.0.dist-info/METADATA
Youtube_Video_Search_API-1.0.dist-info/WHEEL
Youtube_Video_Search_API-1.0.dist-info/top_level.txt
Youtube_Video_Search_API-1.0.dist-info/RECORD
