Metadata-Version: 2.1
Name: Youtube-Video-Search-API
Version: 1.0
Summary: API to search videos on Youtube.
Home-page: https://apimatic.io
Author: APIMatic SDK Generator
Author-email: support@apimatic.io
License: UNKNOWN
Platform: UNKNOWN
Requires-Dist: jsonpickle (>=1.4.1,~=1.4)
Requires-Dist: requests (~=2.25)
Requires-Dist: cachecontrol (~=0.12.6)
Requires-Dist: python-dateutil (~=2.8.1)
Requires-Dist: enum34 (>=1.1.10,~=1.1)
